subdivisions/__init__.py
subdivisions/base.py
subdivisions/builders/__init__.py
subdivisions/builders/events.py
subdivisions/builders/kms.py
subdivisions/builders/sns.py
subdivisions/builders/sqs.py
subdivisions/client.py
subdivisions/config.py
subdivisions/events.py
subdivisions/exceptions.py
subdivisions/policies.py
subdivisions/utils.py
sub_divisions-1.0.2.dist-info/WHEEL
sub_divisions-1.0.2.dist-info/METADATA
sub_divisions-1.0.2.dist-info/RECORD
