Metadata-Version: 2.1
Name: sub-divisions
Version: 1.0.2
Summary: AWS EventBridge based PubSub Library
Home-page: https://github.com/chrismaille/subdivisions
License: GPL-3.0
Keywords: pubsub
Author: Chris Maillefaud
Author-email: chrismaillefaud@gmail.com
Requires-Python: >=3.7,<4.0
Classifier: License :: OSI Approved :: GNU General Public License v3 (GPLv3)
Classifier: Programming Language :: Python :: 3
Classifier: Programming Language :: Python :: 3.7
Requires-Dist: arrow
Requires-Dist: asbool
Requires-Dist: boto3
Requires-Dist: loguru
Requires-Dist: python-dotenv
Requires-Dist: stringcase
Project-URL: Repository, https://github.com/chrismaille/subdivisions
